pygoogalytics/__init__.py
pygoogalytics/ads_wrapper.py
pygoogalytics/client.py
pygoogalytics/framing.py
pygoogalytics/googalytics_wrapper.py
pygoogalytics/googlepandas.py
pygoogalytics/kwp_wrappers.py
pygoogalytics/data/country_iso_codes.csv
pygoogalytics/data/google_ads_location_ids.csv
pygoogalytics/utils/__init__.py
pygoogalytics/utils/ads_reports_parsing.py
pygoogalytics/utils/ga4_parser.py
pygoogalytics/utils/general_utils.py
pygoogalytics/utils/resource_utils.py
pygoogalytics-0.6.17.dist-info/LICENCE.txt
pygoogalytics-0.6.17.dist-info/LICENSE
pygoogalytics-0.6.17.dist-info/METADATA
pygoogalytics-0.6.17.dist-info/WHEEL
pygoogalytics-0.6.17.dist-info/top_level.txt
pygoogalytics-0.6.17.dist-info/RECORD
