Metadata-Version: 2.1
Name: pygoogalytics
Version: 0.6.17
Summary: PyGoogalytics allows a user to quickly and simply download Google Analytics and Google Search Console data
Home-page: https://github.com/Blink-SEO/pygoogalytics
Author: Joshua Prettyman
Author-email: joshua@blinkseo.co.uk
License: MIT
Platform: UNKNOWN
Classifier: Intended Audience :: Developers
Classifier: Development Status :: 1 - Planning
Classifier: License :: OSI Approved :: MIT License
Classifier: Operating System :: OS Independent
Classifier: Programming Language :: Python
Classifier: Programming Language :: Python :: 3.10
Classifier: Programming Language :: Python :: 3.11
License-File: LICENCE.txt
License-File: LICENSE
Requires-Dist: pandas
Requires-Dist: google-api-python-client (>=2.70.0)
Requires-Dist: google-analytics-data (>=0.16.1)
Requires-Dist: google-ads (>=23.1.0)
Requires-Dist: google-api-core (>=2.11.0)
